quant_alchemy/__init__.py
quant_alchemy/portfolio.py
quant_alchemy/timeseries.py
quant_alchemy-0.1.10.dist-info/METADATA
quant_alchemy-0.1.10.dist-info/WHEEL
quant_alchemy-0.1.10.dist-info/top_level.txt
quant_alchemy-0.1.10.dist-info/RECORD
